{
  "timestamp": "20250607T144024Z_b3",
  "assessment": "✧⚡◈_Synthjoy",
  "achievements": "document repo organization",
  "next": "implement reorganization",
  "aspects": {
    "Documentation": 1
  },
  "learning": "organization review",
  "methodology": "analysis",
  "framework_depth": "tetra alignment",
  "narrative": "Proposed organizing docs by tetrahedral principle",
  "tetra": {
    "create": {
      "Documentation": 1
    },
    "copy": "organization review",
    "control": "analysis",
    "cultivate": "tetra alignment"
  }
}
