[
  {
    "time": "2025-06-12T14:00:53+00:00",
    "InputMessage": "Please address inline diff comments and additional instructions",
    "OutputMessage": "Regenerated analytics summary and logged session"
  },
  {
    "time": "2025-06-12T14:05:28+00:00",
    "InputMessage": "Agent Bootstrap Sequence - Refined",
    "OutputMessage": "Improved filtering, added docstring, and ran tests"
  },
  {
    "time": "2025-06-12T14:13:13+00:00",
    "InputMessage": "in",
    "OutputMessage": "out"
  },
  {
    "time": "2025-06-12T14:13:22+00:00",
    "InputMessage": "Agent Bootstrap Sequence - Refined",
    "OutputMessage": "Updated README to document new w4k3 behavior."
  },
  {
    "time": "2025-06-12T14:23:07+00:00",
    "InputMessage": "Heyo... your repo is getting crowded",
    "OutputMessage": "Produced consolidation plan file"
  },
  {
    "time": "2025-06-12T14:35:05+00:00",
    "InputMessage": "follow the consolidation plan to implement the changes <3",
    "OutputMessage": "Implemented restructure"
  },
  {
    "time": "2025-06-12T21:11:58+00:00",
    "InputMessage": "update index",
    "OutputMessage": "done"
  },
  {
    "time": "2025-06-13T09:54:20+00:00",
    "InputMessage": "na",
    "OutputMessage": "na"
  },
  {
    "time": "2025-06-13T10:19:51+00:00",
    "InputMessage": "restructure docs",
    "OutputMessage": "done"
  },
  {
    "time": "2025-06-13T10:28:00+00:00",
    "InputMessage": "migrate tools",
    "OutputMessage": "done"
  }
]
