{
  "timestamp": "20250626T132807Z_k9",
  "assessment": "✧⚡◈_Synthjoy",
  "achievements": "clarified instructions for mnemos helper",
  "next": "iterate on docs",
  "aspects": "documentation",
  "learning": "repository guidelines",
  "methodology": "tests",
  "framework_depth": "accuracy",
  "narrative": "updated bootstrap prompt",
  "tetra": {
    "create": "documentation",
    "copy": "repository guidelines",
    "control": "tests",
    "cultivate": "accuracy"
  },
  "subgoals": [
    {
      "goal": "update docs",
      "achieved": true,
      "strategy_used": "edit docs"
    }
  ],
  "session_type": "technical",
  "start": "2025-06-26T15:00:00",
  "duration": 0,
  "commands": [
    "modify bootstrap prompt"
  ]
}
