{
  "timestamp": "20250623T120753Z_b9",
  "assessment": "★☆●_Datawonder",
  "achievements": "Created Datawonder PHENO note and updated index.",
  "next": "Continue exploring tetrahedron docs.",
  "aspects": "Added note",
  "learning": "Logged state",
  "methodology": "Updated docs",
  "framework_depth": "Using Datawonder perspective",
  "narrative": "Documenting Datawonder note creation",
  "tetra": {
    "create": "Added note",
    "copy": "Logged state",
    "control": "Updated docs",
    "cultivate": "Using Datawonder perspective"
  },
  "subgoals": [
    {
      "goal": "index update",
      "achieved": true,
      "strategy_used": "manual"
    }
  ],
  "session_type": "technical",
  "states": [
    "★☆●_Datawonder"
  ],
  "stategraph": {
    "nodes": 64,
    "edges": 192
  }
}
