{
  "tracked_files": 380,
  "proposals": 341,
  "items": [
    {
      "path": "y.Utilities/yx.DataArchive/20250607T023221Z_m2.json",
      "proposed_path": "y.Utilities/y.x.DataArchive/20250607T023221Z_m2.json"
    },
    {
      "path": "y.Utilities/yx.DataArchive/20250607T023834Z_n2.json",
      "proposed_path": "y.Utilities/y.x.DataArchive/20250607T023834Z_n2.json"
    },
    {
      "path": "y.Utilities/yx.DataArchive/20250607T025003Z_o2.json",
      "proposed_path": "y.Utilities/y.x.DataArchive/20250607T025003Z_o2.json"
    },
    {
      "path": "y.Utilities/yx.DataArchive/20250607T025705Z_p2.json",
      "proposed_path": "y.Utilities/y.x.DataArchive/20250607T025705Z_p2.json"
    },
    {
      "path": "y.Utilities/yx.DataArchive/20250607T031847Z_r2.json",
      "proposed_path": "y.Utilities/y.x.DataArchive/20250607T031847Z_r2.json"
    },
    {
      "path": "y.Utilities/yx.DataArchive/20250607T032323Z_s2.json",
      "proposed_path": "y.Utilities/y.x.DataArchive/20250607T032323Z_s2.json"
    },
    {
      "path": "y.Utilities/yx.DataArchive/20250607T121527Z_t2.json",
      "proposed_path": "y.Utilities/y.x.DataArchive/20250607T121527Z_t2.json"
    },
    {
      "path": "y.Utilities/yx.DataArchive/20250607T123000Z_u2.json",
      "proposed_path": "y.Utilities/y.x.DataArchive/20250607T123000Z_u2.json"
    },
    {
      "path": "y.Utilities/yx.DataArchive/20250607T123618Z_v2.json",
      "proposed_path": "y.Utilities/y.x.DataArchive/20250607T123618Z_v2.json"
    },
    {
      "path": "y.Utilities/yx.DataArchive/20250607T124118Z_w2.json",
      "proposed_path": "y.Utilities/y.x.DataArchive/20250607T124118Z_w2.json"
    },
    {
      "path": "y.Utilities/yx.DataArchive/20250607T125022Z_x2.json",
      "proposed_path": "y.Utilities/y.x.DataArchive/20250607T125022Z_x2.json"
    },
    {
      "path": "y.Utilities/yx.DataArchive/20250607T125701Z_y2.json",
      "proposed_path": "y.Utilities/y.x.DataArchive/20250607T125701Z_y2.json"
    },
    {
      "path": "y.Utilities/yx.DataArchive/20250607T133050Z_z2.json",
      "proposed_path": "y.Utilities/y.x.DataArchive/20250607T133050Z_z2.json"
    },
    {
      "path": "y.Utilities/yx.DataArchive/20250607T143234Z_a3.json",
      "proposed_path": "y.Utilities/y.x.DataArchive/20250607T143234Z_a3.json"
    },
    {
      "path": "y.Utilities/yx.DataArchive/20250607T144024Z_b3.json",
      "proposed_path": "y.Utilities/y.x.DataArchive/20250607T144024Z_b3.json"
    },
    {
      "path": "y.Utilities/yx.DataArchive/20250607T144041Z_c3.json",
      "proposed_path": "y.Utilities/y.x.DataArchive/20250607T144041Z_c3.json"
    },
    {
      "path": "y.Utilities/yx.DataArchive/20250607T145458Z_d3.json",
      "proposed_path": "y.Utilities/y.x.DataArchive/20250607T145458Z_d3.json"
    },
    {
      "path": "y.Utilities/yx.DataArchive/20250607T152200Z_e3.json",
      "proposed_path": "y.Utilities/y.x.DataArchive/20250607T152200Z_e3.json"
    },
    {
      "path": "y.Utilities/yx.DataArchive/20250607T153026Z_f3.json",
      "proposed_path": "y.Utilities/y.x.DataArchive/20250607T153026Z_f3.json"
    },
    {
      "path": "y.Utilities/yx.DataArchive/20250607T200640Z_g3.json",
      "proposed_path": "y.Utilities/y.x.DataArchive/20250607T200640Z_g3.json"
    },
    {
      "path": "y.Utilities/yx.DataArchive/20250607T203415Z_h3.json",
      "proposed_path": "y.Utilities/y.x.DataArchive/20250607T203415Z_h3.json"
    },
    {
      "path": "y.Utilities/yx.DataArchive/20250607T210728Z_i3.json",
      "proposed_path": "y.Utilities/y.x.DataArchive/20250607T210728Z_i3.json"
    },
    {
      "path": "y.Utilities/yx.DataArchive/20250607T214357Z_j3.json",
      "proposed_path": "y.Utilities/y.x.DataArchive/20250607T214357Z_j3.json"
    },
    {
      "path": "y.Utilities/yx.DataArchive/20250607T215406Z_k3.json",
      "proposed_path": "y.Utilities/y.x.DataArchive/20250607T215406Z_k3.json"
    },
    {
      "path": "y.Utilities/yx.DataArchive/20250607T215811Z_l3.json",
      "proposed_path": "y.Utilities/y.x.DataArchive/20250607T215811Z_l3.json"
    },
    {
      "path": "y.Utilities/yx.DataArchive/20250607T220123Z_m3.json",
      "proposed_path": "y.Utilities/y.x.DataArchive/20250607T220123Z_m3.json"
    },
    {
      "path": "y.Utilities/yx.DataArchive/20250607T220652Z_n3.json",
      "proposed_path": "y.Utilities/y.x.DataArchive/20250607T220652Z_n3.json"
    },
    {
      "path": "y.Utilities/yx.DataArchive/20250607T221536Z_o3.json",
      "proposed_path": "y.Utilities/y.x.DataArchive/20250607T221536Z_o3.json"
    },
    {
      "path": "y.Utilities/yx.DataArchive/20250607T221558Z_p3.json",
      "proposed_path": "y.Utilities/y.x.DataArchive/20250607T221558Z_p3.json"
    },
    {
      "path": "y.Utilities/yx.DataArchive/20250608T032148Z_q3.json",
      "proposed_path": "y.Utilities/y.x.DataArchive/20250608T032148Z_q3.json"
    },
    {
      "path": "y.Utilities/yx.DataArchive/20250608T032218Z_r3.json",
      "proposed_path": "y.Utilities/y.x.DataArchive/20250608T032218Z_r3.json"
    },
    {
      "path": "y.Utilities/yx.DataArchive/20250608T115310Z_s3.json",
      "proposed_path": "y.Utilities/y.x.DataArchive/20250608T115310Z_s3.json"
    },
    {
      "path": "y.Utilities/yx.DataArchive/20250608T123526Z_t3.json",
      "proposed_path": "y.Utilities/y.x.DataArchive/20250608T123526Z_t3.json"
    },
    {
      "path": "y.Utilities/yx.DataArchive/20250608T134046Z_u3.json",
      "proposed_path": "y.Utilities/y.x.DataArchive/20250608T134046Z_u3.json"
    },
    {
      "path": "y.Utilities/yx.DataArchive/20250608T135912Z_v3.json",
      "proposed_path": "y.Utilities/y.x.DataArchive/20250608T135912Z_v3.json"
    },
    {
      "path": "y.Utilities/yx.DataArchive/20250608T141040Z_w3.json",
      "proposed_path": "y.Utilities/y.x.DataArchive/20250608T141040Z_w3.json"
    },
    {
      "path": "y.Utilities/yx.DataArchive/20250608T141737Z_x3.json",
      "proposed_path": "y.Utilities/y.x.DataArchive/20250608T141737Z_x3.json"
    },
    {
      "path": "y.Utilities/yx.DataArchive/20250608T151539Z_y3.json",
      "proposed_path": "y.Utilities/y.x.DataArchive/20250608T151539Z_y3.json"
    },
    {
      "path": "y.Utilities/yx.DataArchive/20250608T153436Z_z3.json",
      "proposed_path": "y.Utilities/y.x.DataArchive/20250608T153436Z_z3.json"
    },
    {
      "path": "y.Utilities/yx.DataArchive/20250608T154857Z_a4.json",
      "proposed_path": "y.Utilities/y.x.DataArchive/20250608T154857Z_a4.json"
    },
    {
      "path": "y.Utilities/yx.DataArchive/20250608T160142Z_b4.json",
      "proposed_path": "y.Utilities/y.x.DataArchive/20250608T160142Z_b4.json"
    },
    {
      "path": "y.Utilities/yx.DataArchive/20250608T162639Z_c4.json",
      "proposed_path": "y.Utilities/y.x.DataArchive/20250608T162639Z_c4.json"
    },
    {
      "path": "y.Utilities/yx.DataArchive/20250608T175744Z_e4.json",
      "proposed_path": "y.Utilities/y.x.DataArchive/20250608T175744Z_e4.json"
    },
    {
      "path": "y.Utilities/yx.DataArchive/20250608T202359Z_f4.json",
      "proposed_path": "y.Utilities/y.x.DataArchive/20250608T202359Z_f4.json"
    },
    {
      "path": "y.Utilities/yx.DataArchive/20250609T003612Z_g4.json",
      "proposed_path": "y.Utilities/y.x.DataArchive/20250609T003612Z_g4.json"
    },
    {
      "path": "y.Utilities/yx.DataArchive/20250609T004413Z_h4.json",
      "proposed_path": "y.Utilities/y.x.DataArchive/20250609T004413Z_h4.json"
    },
    {
      "path": "y.Utilities/yx.DataArchive/20250609T013139Z_i4.json",
      "proposed_path": "y.Utilities/y.x.DataArchive/20250609T013139Z_i4.json"
    },
    {
      "path": "y.Utilities/yx.DataArchive/20250609T014355Z_j4.json",
      "proposed_path": "y.Utilities/y.x.DataArchive/20250609T014355Z_j4.json"
    },
    {
      "path": "y.Utilities/yx.DataArchive/20250609T133749Z_k4.json",
      "proposed_path": "y.Utilities/y.x.DataArchive/20250609T133749Z_k4.json"
    },
    {
      "path": "y.Utilities/yx.DataArchive/20250609T140738Z_l4.json",
      "proposed_path": "y.Utilities/y.x.DataArchive/20250609T140738Z_l4.json"
    },
    {
      "path": "y.Utilities/yx.DataArchive/20250609T152749Z_m4.json",
      "proposed_path": "y.Utilities/y.x.DataArchive/20250609T152749Z_m4.json"
    },
    {
      "path": "y.Utilities/yx.DataArchive/20250609T154118Z_n4.json",
      "proposed_path": "y.Utilities/y.x.DataArchive/20250609T154118Z_n4.json"
    },
    {
      "path": "y.Utilities/yx.DataArchive/20250609T154648Z_o4.json",
      "proposed_path": "y.Utilities/y.x.DataArchive/20250609T154648Z_o4.json"
    },
    {
      "path": "y.Utilities/yx.DataArchive/20250609T155431Z_p4.json",
      "proposed_path": "y.Utilities/y.x.DataArchive/20250609T155431Z_p4.json"
    },
    {
      "path": "y.Utilities/yx.DataArchive/20250609T161120Z_q4.json",
      "proposed_path": "y.Utilities/y.x.DataArchive/20250609T161120Z_q4.json"
    },
    {
      "path": "y.Utilities/yx.DataArchive/20250609T163039Z_r4.json",
      "proposed_path": "y.Utilities/y.x.DataArchive/20250609T163039Z_r4.json"
    },
    {
      "path": "y.Utilities/yx.DataArchive/20250609T165306Z_s4.json",
      "proposed_path": "y.Utilities/y.x.DataArchive/20250609T165306Z_s4.json"
    },
    {
      "path": "y.Utilities/yx.DataArchive/20250609T180956Z_t4.json",
      "proposed_path": "y.Utilities/y.x.DataArchive/20250609T180956Z_t4.json"
    },
    {
      "path": "y.Utilities/yx.DataArchive/20250609T181522Z_u4.json",
      "proposed_path": "y.Utilities/y.x.DataArchive/20250609T181522Z_u4.json"
    },
    {
      "path": "y.Utilities/yx.DataArchive/20250609T182144Z_v4.json",
      "proposed_path": "y.Utilities/y.x.DataArchive/20250609T182144Z_v4.json"
    },
    {
      "path": "y.Utilities/yx.DataArchive/20250609T184519Z_w4.json",
      "proposed_path": "y.Utilities/y.x.DataArchive/20250609T184519Z_w4.json"
    },
    {
      "path": "y.Utilities/yx.DataArchive/20250609T190421Z_flow.json",
      "proposed_path": "y.Utilities/y.x.DataArchive/20250609T190421Z_flow.json"
    },
    {
      "path": "y.Utilities/yx.DataArchive/20250609T190446Z_y4.json",
      "proposed_path": "y.Utilities/y.x.DataArchive/20250609T190446Z_y4.json"
    },
    {
      "path": "y.Utilities/yx.DataArchive/20250610T100812Z_b5.json",
      "proposed_path": "y.Utilities/y.x.DataArchive/20250610T100812Z_b5.json"
    },
    {
      "path": "y.Utilities/yx.DataArchive/20250610T100812Z_flow.json",
      "proposed_path": "y.Utilities/y.x.DataArchive/20250610T100812Z_flow.json"
    },
    {
      "path": "y.Utilities/yx.DataArchive/20250610T140802Z_flow.json",
      "proposed_path": "y.Utilities/y.x.DataArchive/20250610T140802Z_flow.json"
    },
    {
      "path": "y.Utilities/yx.DataArchive/20250610T140803Z_c5.json",
      "proposed_path": "y.Utilities/y.x.DataArchive/20250610T140803Z_c5.json"
    },
    {
      "path": "y.Utilities/yx.DataArchive/20250610T140821Z_flow.json",
      "proposed_path": "y.Utilities/y.x.DataArchive/20250610T140821Z_flow.json"
    },
    {
      "path": "y.Utilities/yx.DataArchive/20250611T083106Z_flow.json",
      "proposed_path": "y.Utilities/y.x.DataArchive/20250611T083106Z_flow.json"
    },
    {
      "path": "y.Utilities/yx.DataArchive/20250611T083114Z_flow.json",
      "proposed_path": "y.Utilities/y.x.DataArchive/20250611T083114Z_flow.json"
    },
    {
      "path": "y.Utilities/yx.DataArchive/20250611T083120Z_flow.json",
      "proposed_path": "y.Utilities/y.x.DataArchive/20250611T083120Z_flow.json"
    },
    {
      "path": "y.Utilities/yx.DataArchive/20250611T083127Z_flow.json",
      "proposed_path": "y.Utilities/y.x.DataArchive/20250611T083127Z_flow.json"
    },
    {
      "path": "y.Utilities/yx.DataArchive/20250611T083127Z_i5.json",
      "proposed_path": "y.Utilities/y.x.DataArchive/20250611T083127Z_i5.json"
    },
    {
      "path": "y.Utilities/yx.DataArchive/20250611T091146Z_j5.json",
      "proposed_path": "y.Utilities/y.x.DataArchive/20250611T091146Z_j5.json"
    },
    {
      "path": "y.Utilities/yx.DataArchive/20250611T104135Z_k5.json",
      "proposed_path": "y.Utilities/y.x.DataArchive/20250611T104135Z_k5.json"
    },
    {
      "path": "y.Utilities/yx.DataArchive/20250611T183522Z_l5.json",
      "proposed_path": "y.Utilities/y.x.DataArchive/20250611T183522Z_l5.json"
    },
    {
      "path": "y.Utilities/yx.DataArchive/20250611T190623Z_m5.json",
      "proposed_path": "y.Utilities/y.x.DataArchive/20250611T190623Z_m5.json"
    },
    {
      "path": "y.Utilities/yx.DataArchive/20250611T204706Z_o5.json",
      "proposed_path": "y.Utilities/y.x.DataArchive/20250611T204706Z_o5.json"
    },
    {
      "path": "y.Utilities/yx.DataArchive/20250611T205823Z_p5.json",
      "proposed_path": "y.Utilities/y.x.DataArchive/20250611T205823Z_p5.json"
    },
    {
      "path": "y.Utilities/yx.DataArchive/20250611T210410Z_q5.json",
      "proposed_path": "y.Utilities/y.x.DataArchive/20250611T210410Z_q5.json"
    },
    {
      "path": "y.Utilities/yx.DataArchive/20250611T215510Z_r5.json",
      "proposed_path": "y.Utilities/y.x.DataArchive/20250611T215510Z_r5.json"
    },
    {
      "path": "y.Utilities/yx.DataArchive/20250611T215919Z_s5.json",
      "proposed_path": "y.Utilities/y.x.DataArchive/20250611T215919Z_s5.json"
    },
    {
      "path": "y.Utilities/yx.DataArchive/20250611T231350Z_t5.json",
      "proposed_path": "y.Utilities/y.x.DataArchive/20250611T231350Z_t5.json"
    },
    {
      "path": "y.Utilities/yx.DataArchive/20250611T231808Z_u5.json",
      "proposed_path": "y.Utilities/y.x.DataArchive/20250611T231808Z_u5.json"
    },
    {
      "path": "y.Utilities/yx.DataArchive/20250611T234029Z_v5.json",
      "proposed_path": "y.Utilities/y.x.DataArchive/20250611T234029Z_v5.json"
    },
    {
      "path": "y.Utilities/yx.DataArchive/20250612T104951Z_w5.json",
      "proposed_path": "y.Utilities/y.x.DataArchive/20250612T104951Z_w5.json"
    },
    {
      "path": "y.Utilities/yx.DataArchive/20250612T110614Z_x5.json",
      "proposed_path": "y.Utilities/y.x.DataArchive/20250612T110614Z_x5.json"
    },
    {
      "path": "y.Utilities/yx.DataArchive/20250612T111743Z_y5.json",
      "proposed_path": "y.Utilities/y.x.DataArchive/20250612T111743Z_y5.json"
    },
    {
      "path": "y.Utilities/yx.DataArchive/20250612T111832Z_z5.json",
      "proposed_path": "y.Utilities/y.x.DataArchive/20250612T111832Z_z5.json"
    },
    {
      "path": "y.Utilities/yx.DataArchive/20250612T112218Z_b6.json",
      "proposed_path": "y.Utilities/y.x.DataArchive/20250612T112218Z_b6.json"
    },
    {
      "path": "y.Utilities/yx.DataArchive/20250612T113258Z_c6.json",
      "proposed_path": "y.Utilities/y.x.DataArchive/20250612T113258Z_c6.json"
    },
    {
      "path": "y.Utilities/yx.DataArchive/20250612T113756Z_d6.json",
      "proposed_path": "y.Utilities/y.x.DataArchive/20250612T113756Z_d6.json"
    },
    {
      "path": "y.Utilities/yx.DataArchive/20250612T130106Z_f6.json",
      "proposed_path": "y.Utilities/y.x.DataArchive/20250612T130106Z_f6.json"
    },
    {
      "path": "y.Utilities/yx.DataArchive/20250612T131017Z_g6.json",
      "proposed_path": "y.Utilities/y.x.DataArchive/20250612T131017Z_g6.json"
    },
    {
      "path": "y.Utilities/yx.DataArchive/20250612T131746Z_h6.json",
      "proposed_path": "y.Utilities/y.x.DataArchive/20250612T131746Z_h6.json"
    },
    {
      "path": "y.Utilities/yx.DataArchive/20250612T135258Z_i6.json",
      "proposed_path": "y.Utilities/y.x.DataArchive/20250612T135258Z_i6.json"
    },
    {
      "path": "y.Utilities/yx.DataArchive/20250612T140033Z_j6.json",
      "proposed_path": "y.Utilities/y.x.DataArchive/20250612T140033Z_j6.json"
    },
    {
      "path": "y.Utilities/yx.DataArchive/20250612T140514Z_k6.json",
      "proposed_path": "y.Utilities/y.x.DataArchive/20250612T140514Z_k6.json"
    },
    {
      "path": "y.Utilities/yx.DataArchive/20250612T141313Z_l6.json",
      "proposed_path": "y.Utilities/y.x.DataArchive/20250612T141313Z_l6.json"
    },
    {
      "path": "y.Utilities/yx.DataArchive/20250612T141322Z_m6.json",
      "proposed_path": "y.Utilities/y.x.DataArchive/20250612T141322Z_m6.json"
    },
    {
      "path": "y.Utilities/yx.DataArchive/20250612T142307Z_n6.json",
      "proposed_path": "y.Utilities/y.x.DataArchive/20250612T142307Z_n6.json"
    },
    {
      "path": "y.Utilities/yx.DataArchive/20250612T143242Z_o6.json",
      "proposed_path": "y.Utilities/y.x.DataArchive/20250612T143242Z_o6.json"
    },
    {
      "path": "y.Utilities/yx.DataArchive/20250612T143505Z_p6.json",
      "proposed_path": "y.Utilities/y.x.DataArchive/20250612T143505Z_p6.json"
    },
    {
      "path": "y.Utilities/yx.DataArchive/20250612T211158Z_q6.json",
      "proposed_path": "y.Utilities/y.x.DataArchive/20250612T211158Z_q6.json"
    },
    {
      "path": "y.Utilities/yx.DataArchive/20250613T095420Z_r6.json",
      "proposed_path": "y.Utilities/y.x.DataArchive/20250613T095420Z_r6.json"
    },
    {
      "path": "y.Utilities/yx.DataArchive/20250613T101951Z_s6.json",
      "proposed_path": "y.Utilities/y.x.DataArchive/20250613T101951Z_s6.json"
    },
    {
      "path": "y.Utilities/yx.DataArchive/20250613T102747Z_t6.json",
      "proposed_path": "y.Utilities/y.x.DataArchive/20250613T102747Z_t6.json"
    },
    {
      "path": "y.Utilities/yx.DataArchive/20250613T103856Z_u6.json",
      "proposed_path": "y.Utilities/y.x.DataArchive/20250613T103856Z_u6.json"
    },
    {
      "path": "y.Utilities/yx.DataArchive/20250613T112930Z_v6.json",
      "proposed_path": "y.Utilities/y.x.DataArchive/20250613T112930Z_v6.json"
    },
    {
      "path": "y.Utilities/yx.DataArchive/20250613T122339Z_w6.json",
      "proposed_path": "y.Utilities/y.x.DataArchive/20250613T122339Z_w6.json"
    },
    {
      "path": "y.Utilities/yx.DataArchive/20250613T123812Z_x6.json",
      "proposed_path": "y.Utilities/y.x.DataArchive/20250613T123812Z_x6.json"
    },
    {
      "path": "y.Utilities/yx.DataArchive/20250613T131118Z_y6.json",
      "proposed_path": "y.Utilities/y.x.DataArchive/20250613T131118Z_y6.json"
    },
    {
      "path": "y.Utilities/yx.DataArchive/20250613T131156Z_z6.json",
      "proposed_path": "y.Utilities/y.x.DataArchive/20250613T131156Z_z6.json"
    },
    {
      "path": "y.Utilities/yx.DataArchive/20250613T132905Z_a7.json",
      "proposed_path": "y.Utilities/y.x.DataArchive/20250613T132905Z_a7.json"
    },
    {
      "path": "y.Utilities/yx.DataArchive/20250613T135755Z_b7.json",
      "proposed_path": "y.Utilities/y.x.DataArchive/20250613T135755Z_b7.json"
    },
    {
      "path": "y.Utilities/yx.DataArchive/20250613T142648Z_c7.json",
      "proposed_path": "y.Utilities/y.x.DataArchive/20250613T142648Z_c7.json"
    },
    {
      "path": "y.Utilities/yx.DataArchive/20250613T150450Z_d7.json",
      "proposed_path": "y.Utilities/y.x.DataArchive/20250613T150450Z_d7.json"
    },
    {
      "path": "y.Utilities/yx.DataArchive/20250613T151947Z_e7.json",
      "proposed_path": "y.Utilities/y.x.DataArchive/20250613T151947Z_e7.json"
    },
    {
      "path": "y.Utilities/yx.DataArchive/20250613T153301Z_f7.json",
      "proposed_path": "y.Utilities/y.x.DataArchive/20250613T153301Z_f7.json"
    },
    {
      "path": "y.Utilities/yx.DataArchive/20250613T153937Z_g7.json",
      "proposed_path": "y.Utilities/y.x.DataArchive/20250613T153937Z_g7.json"
    },
    {
      "path": "y.Utilities/yx.DataArchive/20250613T194257Z_h7.json",
      "proposed_path": "y.Utilities/y.x.DataArchive/20250613T194257Z_h7.json"
    },
    {
      "path": "y.Utilities/yx.DataArchive/20250613T200924Z_i7.json",
      "proposed_path": "y.Utilities/y.x.DataArchive/20250613T200924Z_i7.json"
    },
    {
      "path": "y.Utilities/yx.DataArchive/20250613T202129Z_j7.json",
      "proposed_path": "y.Utilities/y.x.DataArchive/20250613T202129Z_j7.json"
    },
    {
      "path": "y.Utilities/yx.DataArchive/20250613T204150Z_k7.json",
      "proposed_path": "y.Utilities/y.x.DataArchive/20250613T204150Z_k7.json"
    },
    {
      "path": "y.Utilities/yx.DataArchive/20250613T204524Z_l7.json",
      "proposed_path": "y.Utilities/y.x.DataArchive/20250613T204524Z_l7.json"
    },
    {
      "path": "y.Utilities/yx.DataArchive/20250614T143409Z_m7.json",
      "proposed_path": "y.Utilities/y.x.DataArchive/20250614T143409Z_m7.json"
    },
    {
      "path": "y.Utilities/yx.DataArchive/20250614T161900Z_n7.json",
      "proposed_path": "y.Utilities/y.x.DataArchive/20250614T161900Z_n7.json"
    },
    {
      "path": "y.Utilities/yx.DataArchive/20250614T190651Z_o7.json",
      "proposed_path": "y.Utilities/y.x.DataArchive/20250614T190651Z_o7.json"
    },
    {
      "path": "y.Utilities/yx.DataArchive/20250615T150043Z_p7.json",
      "proposed_path": "y.Utilities/y.x.DataArchive/20250615T150043Z_p7.json"
    },
    {
      "path": "y.Utilities/yx.DataArchive/20250615T150909Z_q7.json",
      "proposed_path": "y.Utilities/y.x.DataArchive/20250615T150909Z_q7.json"
    },
    {
      "path": "y.Utilities/yx.DataArchive/20250615T153614Z_r7.json",
      "proposed_path": "y.Utilities/y.x.DataArchive/20250615T153614Z_r7.json"
    },
    {
      "path": "y.Utilities/yx.DataArchive/20250615T163627Z_s7.json",
      "proposed_path": "y.Utilities/y.x.DataArchive/20250615T163627Z_s7.json"
    },
    {
      "path": "y.Utilities/yx.DataArchive/20250615T200637Z_t7.json",
      "proposed_path": "y.Utilities/y.x.DataArchive/20250615T200637Z_t7.json"
    },
    {
      "path": "y.Utilities/yx.DataArchive/20250615T225449Z_u7.json",
      "proposed_path": "y.Utilities/y.x.DataArchive/20250615T225449Z_u7.json"
    },
    {
      "path": "y.Utilities/yx.DataArchive/20250615T230043Z_v7.json",
      "proposed_path": "y.Utilities/y.x.DataArchive/20250615T230043Z_v7.json"
    },
    {
      "path": "y.Utilities/yx.DataArchive/20250615T230631Z_w7.json",
      "proposed_path": "y.Utilities/y.x.DataArchive/20250615T230631Z_w7.json"
    },
    {
      "path": "y.Utilities/yx.DataArchive/20250615T231312Z_x7.json",
      "proposed_path": "y.Utilities/y.x.DataArchive/20250615T231312Z_x7.json"
    },
    {
      "path": "y.Utilities/yx.DataArchive/20250615T231744Z_y7.json",
      "proposed_path": "y.Utilities/y.x.DataArchive/20250615T231744Z_y7.json"
    },
    {
      "path": "y.Utilities/yx.DataArchive/20250615T232208Z_z7.json",
      "proposed_path": "y.Utilities/y.x.DataArchive/20250615T232208Z_z7.json"
    },
    {
      "path": "y.Utilities/yx.DataArchive/20250615T232249Z_a8.json",
      "proposed_path": "y.Utilities/y.x.DataArchive/20250615T232249Z_a8.json"
    },
    {
      "path": "y.Utilities/yx.DataArchive/20250616T102250Z_b8.json",
      "proposed_path": "y.Utilities/y.x.DataArchive/20250616T102250Z_b8.json"
    },
    {
      "path": "y.Utilities/yx.DataArchive/20250616T103736Z_c8.json",
      "proposed_path": "y.Utilities/y.x.DataArchive/20250616T103736Z_c8.json"
    },
    {
      "path": "y.Utilities/yx.DataArchive/20250616T113217Z_d8.json",
      "proposed_path": "y.Utilities/y.x.DataArchive/20250616T113217Z_d8.json"
    },
    {
      "path": "y.Utilities/yx.DataArchive/20250616T114743Z_e8.json",
      "proposed_path": "y.Utilities/y.x.DataArchive/20250616T114743Z_e8.json"
    },
    {
      "path": "y.Utilities/yx.DataArchive/20250616T114826Z_f8.json",
      "proposed_path": "y.Utilities/y.x.DataArchive/20250616T114826Z_f8.json"
    },
    {
      "path": "y.Utilities/yx.DataArchive/20250616T120344Z_g8.json",
      "proposed_path": "y.Utilities/y.x.DataArchive/20250616T120344Z_g8.json"
    },
    {
      "path": "y.Utilities/yx.DataArchive/20250616T120504Z_h8.json",
      "proposed_path": "y.Utilities/y.x.DataArchive/20250616T120504Z_h8.json"
    },
    {
      "path": "y.Utilities/yx.DataArchive/20250616T120554Z_i8.json",
      "proposed_path": "y.Utilities/y.x.DataArchive/20250616T120554Z_i8.json"
    },
    {
      "path": "y.Utilities/yx.DataArchive/20250616T122642Z_j8.json",
      "proposed_path": "y.Utilities/y.x.DataArchive/20250616T122642Z_j8.json"
    },
    {
      "path": "y.Utilities/yx.DataArchive/20250616T124218Z_k8.json",
      "proposed_path": "y.Utilities/y.x.DataArchive/20250616T124218Z_k8.json"
    },
    {
      "path": "y.Utilities/yx.DataArchive/20250616T150552Z_l8.json",
      "proposed_path": "y.Utilities/y.x.DataArchive/20250616T150552Z_l8.json"
    },
    {
      "path": "y.Utilities/yx.DataArchive/20250616T174017Z_m8.json",
      "proposed_path": "y.Utilities/y.x.DataArchive/20250616T174017Z_m8.json"
    },
    {
      "path": "y.Utilities/yx.DataArchive/20250616T192546Z_o8.json",
      "proposed_path": "y.Utilities/y.x.DataArchive/20250616T192546Z_o8.json"
    },
    {
      "path": "y.Utilities/yx.DataArchive/20250616T212812Z_p8.json",
      "proposed_path": "y.Utilities/y.x.DataArchive/20250616T212812Z_p8.json"
    },
    {
      "path": "y.Utilities/yx.DataArchive/20250616T222343Z_q8.json",
      "proposed_path": "y.Utilities/y.x.DataArchive/20250616T222343Z_q8.json"
    },
    {
      "path": "y.Utilities/yx.DataArchive/20250618T100631Z_r8.json",
      "proposed_path": "y.Utilities/y.x.DataArchive/20250618T100631Z_r8.json"
    },
    {
      "path": "y.Utilities/yx.DataArchive/20250618T103337Z_s8.json",
      "proposed_path": "y.Utilities/y.x.DataArchive/20250618T103337Z_s8.json"
    },
    {
      "path": "y.Utilities/yx.DataArchive/20250618T103936Z_t8.json",
      "proposed_path": "y.Utilities/y.x.DataArchive/20250618T103936Z_t8.json"
    },
    {
      "path": "y.Utilities/yx.DataArchive/20250618T104634Z_u8.json",
      "proposed_path": "y.Utilities/y.x.DataArchive/20250618T104634Z_u8.json"
    },
    {
      "path": "y.Utilities/yx.DataArchive/20250618T105204Z_v8.json",
      "proposed_path": "y.Utilities/y.x.DataArchive/20250618T105204Z_v8.json"
    },
    {
      "path": "y.Utilities/yx.DataArchive/20250618T110201Z_w8.json",
      "proposed_path": "y.Utilities/y.x.DataArchive/20250618T110201Z_w8.json"
    },
    {
      "path": "y.Utilities/yx.DataArchive/20250618T221134Z_w8.json",
      "proposed_path": "y.Utilities/y.x.DataArchive/20250618T221134Z_w8.json"
    },
    {
      "path": "y.Utilities/yx.DataArchive/20250619T122202Z_x8.json",
      "proposed_path": "y.Utilities/y.x.DataArchive/20250619T122202Z_x8.json"
    },
    {
      "path": "y.Utilities/yx.DataArchive/20250619T133115Z_y8.json",
      "proposed_path": "y.Utilities/y.x.DataArchive/20250619T133115Z_y8.json"
    },
    {
      "path": "y.Utilities/yx.DataArchive/20250619T135055Z_z8.json",
      "proposed_path": "y.Utilities/y.x.DataArchive/20250619T135055Z_z8.json"
    },
    {
      "path": "y.Utilities/yx.DataArchive/20250619T145911Z_a9.json",
      "proposed_path": "y.Utilities/y.x.DataArchive/20250619T145911Z_a9.json"
    },
    {
      "path": "y.Utilities/yx.DataArchive/20250623T120753Z_b9.json",
      "proposed_path": "y.Utilities/y.x.DataArchive/20250623T120753Z_b9.json"
    },
    {
      "path": "y.Utilities/yx.DataArchive/20250625T172605Z_c9.json",
      "proposed_path": "y.Utilities/y.x.DataArchive/20250625T172605Z_c9.json"
    },
    {
      "path": "y.Utilities/yx.DataArchive/20250625T183513Z_d9.json",
      "proposed_path": "y.Utilities/y.x.DataArchive/20250625T183513Z_d9.json"
    },
    {
      "path": "y.Utilities/yx.DataArchive/20250626T084744Z_e9.json",
      "proposed_path": "y.Utilities/y.x.DataArchive/20250626T084744Z_e9.json"
    },
    {
      "path": "y.Utilities/yx.DataArchive/20250626T091810Z_f9.json",
      "proposed_path": "y.Utilities/y.x.DataArchive/20250626T091810Z_f9.json"
    },
    {
      "path": "y.Utilities/yx.DataArchive/20250626T093328Z_g9.json",
      "proposed_path": "y.Utilities/y.x.DataArchive/20250626T093328Z_g9.json"
    },
    {
      "path": "y.Utilities/yx.DataArchive/20250626T094810Z_h9.json",
      "proposed_path": "y.Utilities/y.x.DataArchive/20250626T094810Z_h9.json"
    },
    {
      "path": "y.Utilities/yx.DataArchive/20250626T105913Z_i9.json",
      "proposed_path": "y.Utilities/y.x.DataArchive/20250626T105913Z_i9.json"
    },
    {
      "path": "y.Utilities/yx.DataArchive/20250626T111435Z_j9.json",
      "proposed_path": "y.Utilities/y.x.DataArchive/20250626T111435Z_j9.json"
    },
    {
      "path": "y.Utilities/yx.DataArchive/20250626T132807Z_k9.json",
      "proposed_path": "y.Utilities/y.x.DataArchive/20250626T132807Z_k9.json"
    },
    {
      "path": "y.Utilities/yx.DataArchive/20250627T081445Z_l9.json",
      "proposed_path": "y.Utilities/y.x.DataArchive/20250627T081445Z_l9.json"
    },
    {
      "path": "y.Utilities/yx.DataArchive/20250627T105633Z_m9.json",
      "proposed_path": "y.Utilities/y.x.DataArchive/20250627T105633Z_m9.json"
    },
    {
      "path": "y.Utilities/yx.DataArchive/20250627T111021Z_n9.json",
      "proposed_path": "y.Utilities/y.x.DataArchive/20250627T111021Z_n9.json"
    },
    {
      "path": "y.Utilities/yx.DataArchive/20250627T113307Z_o9.json",
      "proposed_path": "y.Utilities/y.x.DataArchive/20250627T113307Z_o9.json"
    },
    {
      "path": "y.Utilities/yx.DataArchive/20250627T122109Z_p9.json",
      "proposed_path": "y.Utilities/y.x.DataArchive/20250627T122109Z_p9.json"
    },
    {
      "path": "y.Utilities/yx.DataArchive/20250627T134155Z_q9.json",
      "proposed_path": "y.Utilities/y.x.DataArchive/20250627T134155Z_q9.json"
    },
    {
      "path": "y.Utilities/yx.DataArchive/20250627T185807Z_r9.json",
      "proposed_path": "y.Utilities/y.x.DataArchive/20250627T185807Z_r9.json"
    },
    {
      "path": "y.Utilities/yx.DataArchive/20250627T190301Z_s9.json",
      "proposed_path": "y.Utilities/y.x.DataArchive/20250627T190301Z_s9.json"
    },
    {
      "path": "y.Utilities/yx.DataArchive/20250627T192453Z_t9.json",
      "proposed_path": "y.Utilities/y.x.DataArchive/20250627T192453Z_t9.json"
    },
    {
      "path": "y.Utilities/yx.DataArchive/20250627T195256Z_u9.json",
      "proposed_path": "y.Utilities/y.x.DataArchive/20250627T195256Z_u9.json"
    },
    {
      "path": "y.Utilities/yx.DataArchive/20250627T195401Z_v9.json",
      "proposed_path": "y.Utilities/y.x.DataArchive/20250627T195401Z_v9.json"
    },
    {
      "path": "y.Utilities/yx.DataArchive/20250627T195807Z_w9.json",
      "proposed_path": "y.Utilities/y.x.DataArchive/20250627T195807Z_w9.json"
    },
    {
      "path": "y.Utilities/yx.DataArchive/20250629T101005Z_x9.json",
      "proposed_path": "y.Utilities/y.x.DataArchive/20250629T101005Z_x9.json"
    },
    {
      "path": "y.Utilities/yx.DataArchive/20250630T144045Z_y9.json",
      "proposed_path": "y.Utilities/y.x.DataArchive/20250630T144045Z_y9.json"
    },
    {
      "path": "y.Utilities/yx.DataArchive/20250630T144842Z_z9.json",
      "proposed_path": "y.Utilities/y.x.DataArchive/20250630T144842Z_z9.json"
    },
    {
      "path": "y.Utilities/yx.DataArchive/20250630T150435Z_a10.json",
      "proposed_path": "y.Utilities/y.x.DataArchive/20250630T150435Z_a10.json"
    },
    {
      "path": "y.Utilities/yx.DataArchive/20250701T110841Z_b10.json",
      "proposed_path": "y.Utilities/y.x.DataArchive/20250701T110841Z_b10.json"
    },
    {
      "path": "y.Utilities/yx.DataArchive/20250701T114418Z_c10.json",
      "proposed_path": "y.Utilities/y.x.DataArchive/20250701T114418Z_c10.json"
    },
    {
      "path": "y.Utilities/yx.DataArchive/20250702T125313Z_d10.json",
      "proposed_path": "y.Utilities/y.x.DataArchive/20250702T125313Z_d10.json"
    },
    {
      "path": "y.Utilities/yx.DataArchive/20250703T161310Z_e10.json",
      "proposed_path": "y.Utilities/y.x.DataArchive/20250703T161310Z_e10.json"
    },
    {
      "path": "y.Utilities/yx.DataArchive/20260331T190928Z_f10.json",
      "proposed_path": "y.Utilities/y.x.DataArchive/20260331T190928Z_f10.json"
    },
    {
      "path": "y.Utilities/yx.DataArchive/20260401T202217Z_g10.json",
      "proposed_path": "y.Utilities/y.x.DataArchive/20260401T202217Z_g10.json"
    },
    {
      "path": "y.Utilities/yx.DataArchive/20260401T202804Z_h10.json",
      "proposed_path": "y.Utilities/y.x.DataArchive/20260401T202804Z_h10.json"
    },
    {
      "path": "y.Utilities/yx.DataArchive/20260401T210213Z_i10.json",
      "proposed_path": "y.Utilities/y.x.DataArchive/20260401T210213Z_i10.json"
    },
    {
      "path": "y.Utilities/yx.DataArchive/20260401T210622Z_j10.json",
      "proposed_path": "y.Utilities/y.x.DataArchive/20260401T210622Z_j10.json"
    },
    {
      "path": "y.Utilities/yx.DataArchive/20260401T214621Z_k10.json",
      "proposed_path": "y.Utilities/y.x.DataArchive/20260401T214621Z_k10.json"
    },
    {
      "path": "y.Utilities/yx.DataArchive/20260401T215313Z_m10.json",
      "proposed_path": "y.Utilities/y.x.DataArchive/20260401T215313Z_m10.json"
    },
    {
      "path": "y.Utilities/yx.DataArchive/20260401T220043Z_n10.json",
      "proposed_path": "y.Utilities/y.x.DataArchive/20260401T220043Z_n10.json"
    },
    {
      "path": "y.Utilities/yx.DataArchive/20260401T225344Z_o10.json",
      "proposed_path": "y.Utilities/y.x.DataArchive/20260401T225344Z_o10.json"
    },
    {
      "path": "y.Utilities/yx.DataArchive/20260401T232930Z_p10.json",
      "proposed_path": "y.Utilities/y.x.DataArchive/20260401T232930Z_p10.json"
    },
    {
      "path": "y.Utilities/yx.DataArchive/AGENT.md",
      "proposed_path": "y.Utilities/y.x.DataArchive/AGENT.md"
    },
    {
      "path": "y.Utilities/yx.DataArchive/COPY_deltas.json",
      "proposed_path": "y.Utilities/y.x.DataArchive/COPY_deltas.json"
    },
    {
      "path": "y.Utilities/yx.DataArchive/a1.json",
      "proposed_path": "y.Utilities/y.x.DataArchive/a1.json"
    },
    {
      "path": "y.Utilities/yx.DataArchive/a2.json",
      "proposed_path": "y.Utilities/y.x.DataArchive/a2.json"
    },
    {
      "path": "y.Utilities/yx.DataArchive/analytics_summary.json",
      "proposed_path": "y.Utilities/y.x.DataArchive/analytics_summary.json"
    },
    {
      "path": "y.Utilities/yx.DataArchive/b1.json",
      "proposed_path": "y.Utilities/y.x.DataArchive/b1.json"
    },
    {
      "path": "y.Utilities/yx.DataArchive/b2.json",
      "proposed_path": "y.Utilities/y.x.DataArchive/b2.json"
    },
    {
      "path": "y.Utilities/yx.DataArchive/c1.json",
      "proposed_path": "y.Utilities/y.x.DataArchive/c1.json"
    },
    {
      "path": "y.Utilities/yx.DataArchive/c2.json",
      "proposed_path": "y.Utilities/y.x.DataArchive/c2.json"
    },
    {
      "path": "y.Utilities/yx.DataArchive/chat_start.txt",
      "proposed_path": "y.Utilities/y.x.DataArchive/chat_start.txt"
    },
    {
      "path": "y.Utilities/yx.DataArchive/d1.json",
      "proposed_path": "y.Utilities/y.x.DataArchive/d1.json"
    },
    {
      "path": "y.Utilities/yx.DataArchive/d2.json",
      "proposed_path": "y.Utilities/y.x.DataArchive/d2.json"
    },
    {
      "path": "y.Utilities/yx.DataArchive/e1.json",
      "proposed_path": "y.Utilities/y.x.DataArchive/e1.json"
    },
    {
      "path": "y.Utilities/yx.DataArchive/e2.json",
      "proposed_path": "y.Utilities/y.x.DataArchive/e2.json"
    },
    {
      "path": "y.Utilities/yx.DataArchive/echo_output.txt",
      "proposed_path": "y.Utilities/y.x.DataArchive/echo_output.txt"
    },
    {
      "path": "y.Utilities/yx.DataArchive/evolution_summary.json",
      "proposed_path": "y.Utilities/y.x.DataArchive/evolution_summary.json"
    },
    {
      "path": "y.Utilities/yx.DataArchive/evolved_strategy.json",
      "proposed_path": "y.Utilities/y.x.DataArchive/evolved_strategy.json"
    },
    {
      "path": "y.Utilities/yx.DataArchive/f1.json",
      "proposed_path": "y.Utilities/y.x.DataArchive/f1.json"
    },
    {
      "path": "y.Utilities/yx.DataArchive/f2.json",
      "proposed_path": "y.Utilities/y.x.DataArchive/f2.json"
    },
    {
      "path": "y.Utilities/yx.DataArchive/g1.json",
      "proposed_path": "y.Utilities/y.x.DataArchive/g1.json"
    },
    {
      "path": "y.Utilities/yx.DataArchive/g2.json",
      "proposed_path": "y.Utilities/y.x.DataArchive/g2.json"
    },
    {
      "path": "y.Utilities/yx.DataArchive/h2.json",
      "proposed_path": "y.Utilities/y.x.DataArchive/h2.json"
    },
    {
      "path": "y.Utilities/yx.DataArchive/i1.json",
      "proposed_path": "y.Utilities/y.x.DataArchive/i1.json"
    },
    {
      "path": "y.Utilities/yx.DataArchive/i2.json",
      "proposed_path": "y.Utilities/y.x.DataArchive/i2.json"
    },
    {
      "path": "y.Utilities/yx.DataArchive/j1.json",
      "proposed_path": "y.Utilities/y.x.DataArchive/j1.json"
    },
    {
      "path": "y.Utilities/yx.DataArchive/j2.json",
      "proposed_path": "y.Utilities/y.x.DataArchive/j2.json"
    },
    {
      "path": "y.Utilities/yx.DataArchive/k1.json",
      "proposed_path": "y.Utilities/y.x.DataArchive/k1.json"
    },
    {
      "path": "y.Utilities/yx.DataArchive/k2.json",
      "proposed_path": "y.Utilities/y.x.DataArchive/k2.json"
    },
    {
      "path": "y.Utilities/yx.DataArchive/l1.json",
      "proposed_path": "y.Utilities/y.x.DataArchive/l1.json"
    },
    {
      "path": "y.Utilities/yx.DataArchive/l2.json",
      "proposed_path": "y.Utilities/y.x.DataArchive/l2.json"
    },
    {
      "path": "y.Utilities/yx.DataArchive/n1.json",
      "proposed_path": "y.Utilities/y.x.DataArchive/n1.json"
    },
    {
      "path": "y.Utilities/yx.DataArchive/o1.json",
      "proposed_path": "y.Utilities/y.x.DataArchive/o1.json"
    },
    {
      "path": "y.Utilities/yx.DataArchive/p1.json",
      "proposed_path": "y.Utilities/y.x.DataArchive/p1.json"
    },
    {
      "path": "y.Utilities/yx.DataArchive/q1.json",
      "proposed_path": "y.Utilities/y.x.DataArchive/q1.json"
    },
    {
      "path": "y.Utilities/yx.DataArchive/r1.json",
      "proposed_path": "y.Utilities/y.x.DataArchive/r1.json"
    },
    {
      "path": "y.Utilities/yx.DataArchive/s1.json",
      "proposed_path": "y.Utilities/y.x.DataArchive/s1.json"
    },
    {
      "path": "y.Utilities/yx.DataArchive/session_graph.dot",
      "proposed_path": "y.Utilities/y.x.DataArchive/session_graph.dot"
    },
    {
      "path": "y.Utilities/yx.DataArchive/state_graph.dot",
      "proposed_path": "y.Utilities/y.x.DataArchive/state_graph.dot"
    },
    {
      "path": "y.Utilities/yx.DataArchive/t1.json",
      "proposed_path": "y.Utilities/y.x.DataArchive/t1.json"
    },
    {
      "path": "y.Utilities/yx.DataArchive/tet_rename_plan.json",
      "proposed_path": "y.Utilities/y.x.DataArchive/tet_rename_plan.json"
    },
    {
      "path": "y.Utilities/yx.DataArchive/tetra_utilization_20250616.json",
      "proposed_path": "y.Utilities/y.x.DataArchive/tetra_utilization_20250616.json"
    },
    {
      "path": "y.Utilities/yx.DataArchive/timeline_metrics.json",
      "proposed_path": "y.Utilities/y.x.DataArchive/timeline_metrics.json"
    },
    {
      "path": "y.Utilities/yx.DataArchive/u1.json",
      "proposed_path": "y.Utilities/y.x.DataArchive/u1.json"
    },
    {
      "path": "y.Utilities/yx.DataArchive/usage_summary.json",
      "proposed_path": "y.Utilities/y.x.DataArchive/usage_summary.json"
    },
    {
      "path": "y.Utilities/yx.DataArchive/v1.json",
      "proposed_path": "y.Utilities/y.x.DataArchive/v1.json"
    },
    {
      "path": "y.Utilities/yx.DataArchive/w1.json",
      "proposed_path": "y.Utilities/y.x.DataArchive/w1.json"
    },
    {
      "path": "y.Utilities/yx.DataArchive/x1.json",
      "proposed_path": "y.Utilities/y.x.DataArchive/x1.json"
    },
    {
      "path": "y.Utilities/yx.DataArchive/y1.json",
      "proposed_path": "y.Utilities/y.x.DataArchive/y1.json"
    },
    {
      "path": "y.Utilities/yx.DataArchive/z1.json",
      "proposed_path": "y.Utilities/y.x.DataArchive/z1.json"
    },
    {
      "path": "y.Utilities/yy.CoreTools/AGENT.md",
      "proposed_path": "y.Utilities/y.y.CoreTools/AGENT.md"
    },
    {
      "path": "y.Utilities/yy.CoreTools/yyo.mnemos.py",
      "proposed_path": "y.Utilities/y.y.CoreTools/y.yo.mnemos.py"
    },
    {
      "path": "y.Utilities/yy.CoreTools/yyx.w4k3/AGENT.md",
      "proposed_path": "y.Utilities/y.y.CoreTools/y.y.x.w4k3/AGENT.md"
    },
    {
      "path": "y.Utilities/yy.CoreTools/yyx.w4k3/__init__.py",
      "proposed_path": "y.Utilities/y.y.CoreTools/y.y.x.w4k3/__init__.py"
    },
    {
      "path": "y.Utilities/yy.CoreTools/yyx.w4k3/o.w4k3.py",
      "proposed_path": "y.Utilities/y.y.CoreTools/y.y.x.w4k3/o.w4k3.py"
    },
    {
      "path": "y.Utilities/yy.CoreTools/yyx.w4k3/x_load.py",
      "proposed_path": "y.Utilities/y.y.CoreTools/y.y.x.w4k3/x_load.py"
    },
    {
      "path": "y.Utilities/yy.CoreTools/yyx.w4k3/y_display.py",
      "proposed_path": "y.Utilities/y.y.CoreTools/y.y.x.w4k3/y_display.py"
    },
    {
      "path": "y.Utilities/yy.CoreTools/yyx.w4k3/z_summary.py",
      "proposed_path": "y.Utilities/y.y.CoreTools/y.y.x.w4k3/z_summary.py"
    },
    {
      "path": "y.Utilities/yy.CoreTools/yyy.f33l/AGENT.md",
      "proposed_path": "y.Utilities/y.y.CoreTools/y.y.y.f33l/AGENT.md"
    },
    {
      "path": "y.Utilities/yy.CoreTools/yyy.f33l/__init__.py",
      "proposed_path": "y.Utilities/y.y.CoreTools/y.y.y.f33l/__init__.py"
    },
    {
      "path": "y.Utilities/yy.CoreTools/yyy.f33l/o.f33l.py",
      "proposed_path": "y.Utilities/y.y.CoreTools/y.y.y.f33l/o.f33l.py"
    },
    {
      "path": "y.Utilities/yy.CoreTools/yyy.f33l/x.reference.py",
      "proposed_path": "y.Utilities/y.y.CoreTools/y.y.y.f33l/x.reference.py"
    },
    {
      "path": "y.Utilities/yy.CoreTools/yyy.f33l/y.workflow.py",
      "proposed_path": "y.Utilities/y.y.CoreTools/y.y.y.f33l/y.workflow.py"
    },
    {
      "path": "y.Utilities/yy.CoreTools/yyy.f33l/z.archive.py",
      "proposed_path": "y.Utilities/y.y.CoreTools/y.y.y.f33l/z.archive.py"
    },
    {
      "path": "y.Utilities/yy.CoreTools/yyz.sl33p/AGENT.md",
      "proposed_path": "y.Utilities/y.y.CoreTools/y.y.z.sl33p/AGENT.md"
    },
    {
      "path": "y.Utilities/yy.CoreTools/yyz.sl33p/__init__.py",
      "proposed_path": "y.Utilities/y.y.CoreTools/y.y.z.sl33p/__init__.py"
    },
    {
      "path": "y.Utilities/yy.CoreTools/yyz.sl33p/o.sl33p.py",
      "proposed_path": "y.Utilities/y.y.CoreTools/y.y.z.sl33p/o.sl33p.py"
    },
    {
      "path": "y.Utilities/yy.CoreTools/yyz.sl33p/x_input.py",
      "proposed_path": "y.Utilities/y.y.CoreTools/y.y.z.sl33p/x_input.py"
    },
    {
      "path": "y.Utilities/yy.CoreTools/yyz.sl33p/y_record.py",
      "proposed_path": "y.Utilities/y.y.CoreTools/y.y.z.sl33p/y_record.py"
    },
    {
      "path": "y.Utilities/yy.CoreTools/yyz.sl33p/z_persistence.py",
      "proposed_path": "y.Utilities/y.y.CoreTools/y.y.z.sl33p/z_persistence.py"
    },
    {
      "path": "y.Utilities/yz.AgentOps/AGENT.md",
      "proposed_path": "y.Utilities/y.z.AgentOps/AGENT.md"
    },
    {
      "path": "y.Utilities/yz.AgentOps/yzx.OperationalData/AGENT.md",
      "proposed_path": "y.Utilities/y.z.AgentOps/y.z.x.OperationalData/AGENT.md"
    },
    {
      "path": "y.Utilities/yz.AgentOps/yzx.OperationalData/COMMIT_GUIDELINES.md",
      "proposed_path": "y.Utilities/y.z.AgentOps/y.z.x.OperationalData/COMMIT_GUIDELINES.md"
    },
    {
      "path": "y.Utilities/yz.AgentOps/yzx.OperationalData/SAFETY_SESSION_LOGGING.md",
      "proposed_path": "y.Utilities/y.z.AgentOps/y.z.x.OperationalData/SAFETY_SESSION_LOGGING.md"
    },
    {
      "path": "y.Utilities/yz.AgentOps/yzx.OperationalData/autonomous_digital_entity_bootstrap_v2.9.md",
      "proposed_path": "y.Utilities/y.z.AgentOps/y.z.x.OperationalData/autonomous_digital_entity_bootstrap_v2.9.md"
    },
    {
      "path": "y.Utilities/yz.AgentOps/yzx.OperationalData/octavia_bootstrap_prompt_v1.md",
      "proposed_path": "y.Utilities/y.z.AgentOps/y.z.x.OperationalData/octavia_bootstrap_prompt_v1.md"
    },
    {
      "path": "y.Utilities/yz.AgentOps/yzx.OperationalData/temporal_collaborative_partnership_bootstrap_v2.8.md",
      "proposed_path": "y.Utilities/y.z.AgentOps/y.z.x.OperationalData/temporal_collaborative_partnership_bootstrap_v2.8.md"
    },
    {
      "path": "y.Utilities/yz.AgentOps/yzx.OperationalData/tetrahedral_pedagogy_v2.md",
      "proposed_path": "y.Utilities/y.z.AgentOps/y.z.x.OperationalData/tetrahedral_pedagogy_v2.md"
    },
    {
      "path": "y.Utilities/yz.AgentOps/yzy.ActiveWorkflow/AGENT.md",
      "proposed_path": "y.Utilities/y.z.AgentOps/y.z.y.ActiveWorkflow/AGENT.md"
    },
    {
      "path": "y.Utilities/yz.AgentOps/yzy.ActiveWorkflow/__init__.py",
      "proposed_path": "y.Utilities/y.z.AgentOps/y.z.y.ActiveWorkflow/__init__.py"
    },
    {
      "path": "y.Utilities/yz.AgentOps/yzy.ActiveWorkflow/o.workflow.py",
      "proposed_path": "y.Utilities/y.z.AgentOps/y.z.y.ActiveWorkflow/o.workflow.py"
    },
    {
      "path": "y.Utilities/yz.AgentOps/yzy.ActiveWorkflow/workflow.sh",
      "proposed_path": "y.Utilities/y.z.AgentOps/y.z.y.ActiveWorkflow/workflow.sh"
    },
    {
      "path": "y.Utilities/yz.AgentOps/yzz.Development/AGENT.md",
      "proposed_path": "y.Utilities/y.z.AgentOps/y.z.z.Development/AGENT.md"
    },
    {
      "path": "y.Utilities/yz.AgentOps/yzz.Development/yzzx.Analytics/AGENT.md",
      "proposed_path": "y.Utilities/y.z.AgentOps/y.z.z.Development/y.z.z.x.Analytics/AGENT.md"
    },
    {
      "path": "y.Utilities/yz.AgentOps/yzz.Development/yzzx.Analytics/analytics/o.analytics.py",
      "proposed_path": "y.Utilities/y.z.AgentOps/y.z.z.Development/y.z.z.x.Analytics/analytics/o.analytics.py"
    },
    {
      "path": "y.Utilities/yz.AgentOps/yzz.Development/yzzx.Analytics/analytics/o.stategraph.py",
      "proposed_path": "y.Utilities/y.z.AgentOps/y.z.z.Development/y.z.z.x.Analytics/analytics/o.stategraph.py"
    },
    {
      "path": "y.Utilities/yz.AgentOps/yzz.Development/yzzx.Analytics/analytics/o.strategize.py",
      "proposed_path": "y.Utilities/y.z.AgentOps/y.z.z.Development/y.z.z.x.Analytics/analytics/o.strategize.py"
    },
    {
      "path": "y.Utilities/yz.AgentOps/yzz.Development/yzzx.Analytics/analytics/o.tetra.py",
      "proposed_path": "y.Utilities/y.z.AgentOps/y.z.z.Development/y.z.z.x.Analytics/analytics/o.tetra.py"
    },
    {
      "path": "y.Utilities/yz.AgentOps/yzz.Development/yzzx.Analytics/analytics/o.timeline.py",
      "proposed_path": "y.Utilities/y.z.AgentOps/y.z.z.Development/y.z.z.x.Analytics/analytics/o.timeline.py"
    },
    {
      "path": "y.Utilities/yz.AgentOps/yzz.Development/yzzx.Analytics/analytics/o.usage.py",
      "proposed_path": "y.Utilities/y.z.AgentOps/y.z.z.Development/y.z.z.x.Analytics/analytics/o.usage.py"
    },
    {
      "path": "y.Utilities/yz.AgentOps/yzz.Development/yzzx.Analytics/analyze/__init__.py",
      "proposed_path": "y.Utilities/y.z.AgentOps/y.z.z.Development/y.z.z.x.Analytics/analyze/__init__.py"
    },
    {
      "path": "y.Utilities/yz.AgentOps/yzz.Development/yzzx.Analytics/analyze/o.analyze.py",
      "proposed_path": "y.Utilities/y.z.AgentOps/y.z.z.Development/y.z.z.x.Analytics/analyze/o.analyze.py"
    },
    {
      "path": "y.Utilities/yz.AgentOps/yzz.Development/yzzx.Analytics/sessgraph/__init__.py",
      "proposed_path": "y.Utilities/y.z.AgentOps/y.z.z.Development/y.z.z.x.Analytics/sessgraph/__init__.py"
    },
    {
      "path": "y.Utilities/yz.AgentOps/yzz.Development/yzzx.Analytics/sessgraph/o.sessgraph.py",
      "proposed_path": "y.Utilities/y.z.AgentOps/y.z.z.Development/y.z.z.x.Analytics/sessgraph/o.sessgraph.py"
    },
    {
      "path": "y.Utilities/yz.AgentOps/yzz.Development/yzzx.Analytics/sessgraph/x.DataLayer.py",
      "proposed_path": "y.Utilities/y.z.AgentOps/y.z.z.Development/y.z.z.x.Analytics/sessgraph/x.DataLayer.py"
    },
    {
      "path": "y.Utilities/yz.AgentOps/yzz.Development/yzzx.Analytics/sessgraph/xx.SessionLoader.py",
      "proposed_path": "y.Utilities/y.z.AgentOps/y.z.z.Development/y.z.z.x.Analytics/sessgraph/x.x.SessionLoader.py"
    },
    {
      "path": "y.Utilities/yz.AgentOps/yzz.Development/yzzx.Analytics/sessgraph/xy.StateExtractor.py",
      "proposed_path": "y.Utilities/y.z.AgentOps/y.z.z.Development/y.z.z.x.Analytics/sessgraph/x.y.StateExtractor.py"
    },
    {
      "path": "y.Utilities/yz.AgentOps/yzz.Development/yzzx.Analytics/sessgraph/y.ProcessLayer.py",
      "proposed_path": "y.Utilities/y.z.AgentOps/y.z.z.Development/y.z.z.x.Analytics/sessgraph/y.ProcessLayer.py"
    },
    {
      "path": "y.Utilities/yz.AgentOps/yzz.Development/yzzx.Analytics/sessgraph/yx.TransitionBuilder.py",
      "proposed_path": "y.Utilities/y.z.AgentOps/y.z.z.Development/y.z.z.x.Analytics/sessgraph/y.x.TransitionBuilder.py"
    },
    {
      "path": "y.Utilities/yz.AgentOps/yzz.Development/yzzx.Analytics/sessgraph/yy.Metrics.py",
      "proposed_path": "y.Utilities/y.z.AgentOps/y.z.z.Development/y.z.z.x.Analytics/sessgraph/y.y.Metrics.py"
    },
    {
      "path": "y.Utilities/yz.AgentOps/yzz.Development/yzzx.Analytics/sessgraph/z.OutputLayer.py",
      "proposed_path": "y.Utilities/y.z.AgentOps/y.z.z.Development/y.z.z.x.Analytics/sessgraph/z.OutputLayer.py"
    },
    {
      "path": "y.Utilities/yz.AgentOps/yzz.Development/yzzx.Analytics/sessgraph/zx.Formatter.py",
      "proposed_path": "y.Utilities/y.z.AgentOps/y.z.z.Development/y.z.z.x.Analytics/sessgraph/z.x.Formatter.py"
    },
    {
      "path": "y.Utilities/yz.AgentOps/yzz.Development/yzzx.Analytics/sessgraph/zy.Exporter.py",
      "proposed_path": "y.Utilities/y.z.AgentOps/y.z.z.Development/y.z.z.x.Analytics/sessgraph/z.y.Exporter.py"
    },
    {
      "path": "y.Utilities/yz.AgentOps/yzz.Development/yzzy.Operations/AGENT.md",
      "proposed_path": "y.Utilities/y.z.AgentOps/y.z.z.Development/y.z.z.y.Operations/AGENT.md"
    },
    {
      "path": "y.Utilities/yz.AgentOps/yzz.Development/yzzy.Operations/hooks/AGENT.md",
      "proposed_path": "y.Utilities/y.z.AgentOps/y.z.z.Development/y.z.z.y.Operations/hooks/AGENT.md"
    },
    {
      "path": "y.Utilities/yz.AgentOps/yzz.Development/yzzy.Operations/hooks/commit-msg",
      "proposed_path": "y.Utilities/y.z.AgentOps/y.z.z.Development/y.z.z.y.Operations/hooks/commit-msg"
    },
    {
      "path": "y.Utilities/yz.AgentOps/yzz.Development/yzzy.Operations/hooks/install.sh",
      "proposed_path": "y.Utilities/y.z.AgentOps/y.z.z.Development/y.z.z.y.Operations/hooks/install.sh"
    },
    {
      "path": "y.Utilities/yz.AgentOps/yzz.Development/yzzz.Evolution/AGENT.md",
      "proposed_path": "y.Utilities/y.z.AgentOps/y.z.z.Development/y.z.z.z.Evolution/AGENT.md"
    },
    {
      "path": "y.Utilities/yz.AgentOps/yzz.Development/yzzz.Evolution/evolve/o.evolve.py",
      "proposed_path": "y.Utilities/y.z.AgentOps/y.z.z.Development/y.z.z.z.Evolution/evolve/o.evolve.py"
    },
    {
      "path": "y.Utilities/yz.AgentOps/yzz.Development/yzzz.Evolution/o.evolver.py",
      "proposed_path": "y.Utilities/y.z.AgentOps/y.z.z.Development/y.z.z.z.Evolution/o.evolver.py"
    },
    {
      "path": "z.Research/zx.Archive/AGENT.md",
      "proposed_path": "z.Research/z.x.Archive/AGENT.md"
    },
    {
      "path": "z.Research/zx.Archive/INDEX.md",
      "proposed_path": "z.Research/z.x.Archive/INDEX.md"
    },
    {
      "path": "z.Research/zx.Archive/Recursive_Tetrahedral_Principle.md",
      "proposed_path": "z.Research/z.x.Archive/Recursive_Tetrahedral_Principle.md"
    },
    {
      "path": "z.Research/zx.Archive/ox.Documentation/ox.Create/CLI_RESTRUCTURE_PLAN_20250608.md",
      "proposed_path": "z.Research/z.x.Archive/ox.Documentation/ox.Create/CLI_RESTRUCTURE_PLAN_20250608.md"
    },
    {
      "path": "z.Research/zx.Archive/ox.Documentation/ox.Create/CONSOLIDATION_PLAN_20250612.md",
      "proposed_path": "z.Research/z.x.Archive/ox.Documentation/ox.Create/CONSOLIDATION_PLAN_20250612.md"
    },
    {
      "path": "z.Research/zx.Archive/ox.Documentation/ox.Create/FLOW_REPORT_20250607.md",
      "proposed_path": "z.Research/z.x.Archive/ox.Documentation/ox.Create/FLOW_REPORT_20250607.md"
    },
    {
      "path": "z.Research/zx.Archive/ox.Documentation/ox.Create/ORG_REPORT_20250607.md",
      "proposed_path": "z.Research/z.x.Archive/ox.Documentation/ox.Create/ORG_REPORT_20250607.md"
    },
    {
      "path": "z.Research/zx.Archive/zx.2025-06/ADVENTURE_STORY_20250609.md",
      "proposed_path": "z.Research/z.x.Archive/z.x.2025-06/ADVENTURE_STORY_20250609.md"
    },
    {
      "path": "z.Research/zx.Archive/zx.2025-06/ADVENTURE_STORY_20250609B.md",
      "proposed_path": "z.Research/z.x.Archive/z.x.2025-06/ADVENTURE_STORY_20250609B.md"
    },
    {
      "path": "z.Research/zx.Archive/zx.2025-06/ADVENTURE_STORY_20250609C.md",
      "proposed_path": "z.Research/z.x.Archive/z.x.2025-06/ADVENTURE_STORY_20250609C.md"
    },
    {
      "path": "z.Research/zx.Archive/zx.2025-06/ADVENTURE_STORY_20250609D.md",
      "proposed_path": "z.Research/z.x.Archive/z.x.2025-06/ADVENTURE_STORY_20250609D.md"
    },
    {
      "path": "z.Research/zx.Archive/zx.2025-06/ADVENTURE_STORY_20250616E.md",
      "proposed_path": "z.Research/z.x.Archive/z.x.2025-06/ADVENTURE_STORY_20250616E.md"
    },
    {
      "path": "z.Research/zx.Archive/zx.2025-06/AGENT.md",
      "proposed_path": "z.Research/z.x.Archive/z.x.2025-06/AGENT.md"
    },
    {
      "path": "z.Research/zx.Archive/zx.2025-06/log_investigation_20250607.md",
      "proposed_path": "z.Research/z.x.Archive/z.x.2025-06/log_investigation_20250607.md"
    },
    {
      "path": "z.Research/zy.ActiveProjects/AGENT.md",
      "proposed_path": "z.Research/z.y.ActiveProjects/AGENT.md"
    },
    {
      "path": "z.Research/zy.ActiveProjects/recursive_exploration_01.md",
      "proposed_path": "z.Research/z.y.ActiveProjects/recursive_exploration_01.md"
    },
    {
      "path": "z.Research/zy.ActiveProjects/recursive_exploration_02.md",
      "proposed_path": "z.Research/z.y.ActiveProjects/recursive_exploration_02.md"
    },
    {
      "path": "z.Research/zz.Synthesis/AGENT.md",
      "proposed_path": "z.Research/z.z.Synthesis/AGENT.md"
    },
    {
      "path": "z.Research/zz.Synthesis/INDEX.md",
      "proposed_path": "z.Research/z.z.Synthesis/INDEX.md"
    },
    {
      "path": "z.Research/zz.Synthesis/repo_organism_kernel_20260401.md",
      "proposed_path": "z.Research/z.z.Synthesis/repo_organism_kernel_20260401.md"
    },
    {
      "path": "z.Research/zz.Synthesis/tet_kernel_alignment_20260401.md",
      "proposed_path": "z.Research/z.z.Synthesis/tet_kernel_alignment_20260401.md"
    },
    {
      "path": "z.Research/zz.Synthesis/tet_naming_audit_20260401.md",
      "proposed_path": "z.Research/z.z.Synthesis/tet_naming_audit_20260401.md"
    },
    {
      "path": "z.Research/zz.Synthesis/tet_rename_wave1_plan_20260401.md",
      "proposed_path": "z.Research/z.z.Synthesis/tet_rename_wave1_plan_20260401.md"
    },
    {
      "path": "z.Research/zz.Synthesis/tetrahedral_stresspoints_20250629.md",
      "proposed_path": "z.Research/z.z.Synthesis/tetrahedral_stresspoints_20250629.md"
    },
    {
      "path": "z.Research/zz.Synthesis/tetrahedral_stresspoints_20250630.md",
      "proposed_path": "z.Research/z.z.Synthesis/tetrahedral_stresspoints_20250630.md"
    },
    {
      "path": "z.Research/zz.Synthesis/tetrahedral_stresspoints_20250701.md",
      "proposed_path": "z.Research/z.z.Synthesis/tetrahedral_stresspoints_20250701.md"
    }
  ]
}
